tex2img.cp36-win32.pyd
tex2img-0.9.1.dist-info/LICENSE
tex2img-0.9.1.dist-info/METADATA
tex2img-0.9.1.dist-info/WHEEL
tex2img-0.9.1.dist-info/top_level.txt
tex2img-0.9.1.dist-info/RECORD
