Metadata-Version: 2.1
Name: tex2img
Version: 0.9.1
Summary: a texture decompression C++-extension for Python
Home-page: https://github.com/K0lb3/tex2img
Author: K0lb3
License: UNKNOWN
Download-URL: https://github.com/K0lb3/tex2img/tarball/master
Keywords: astc,atc,pvrtc,etc,crunch
Platform: UNKNOWN
Classifier: License :: OSI Approved :: MIT License
Classifier: Operating System :: OS Independent
Classifier: Intended Audience :: Developers
Classifier: Programming Language :: Python
Classifier: Programming Language :: Python :: 3
Classifier: Programming Language :: Python :: 3.6
Classifier: Programming Language :: Python :: 3.7
Classifier: Programming Language :: Python :: 3.8
Classifier: Topic :: Multimedia :: Graphics
